WatchUI/Ibasic/IBasic.py
WatchUI/Ibasic/__init__.py
WatchUI/WatchUI.py
WatchUI/__init__.py
WatchUI/keywords/Image.py
WatchUI/keywords/PDF.py
WatchUI/keywords/Tesseract.py
WatchUI/keywords/__init__.py
watchui-2.0.13.dist-info/LICENSE
watchui-2.0.13.dist-info/METADATA
watchui-2.0.13.dist-info/WHEEL
watchui-2.0.13.dist-info/entry_points.txt
watchui-2.0.13.dist-info/RECORD
