Metadata-Version: 2.1
Name: watchui
Version: 2.0.13
Summary: RobotFramework library package for automated visual testing.
Home-page: https://github.com/Tesena-smart-testing/WatchUI
License: MIT
Author: Jan Egermaier
Author-email: jan.egermaier@tesena.com
Requires-Python: >=3.9,<4.0
Classifier: License :: OSI Approved :: MIT License
Classifier: Operating System :: OS Independent
Classifier: Programming Language :: Python :: 3
Classifier: Programming Language :: Python :: 3.9
Classifier: Programming Language :: Python :: 3.10
Classifier: Programming Language :: Python :: 3.11
Classifier: Programming Language :: Python :: 3
Requires-Dist: Pillow
Requires-Dist: PyMuPDF
Requires-Dist: imutils
Requires-Dist: numpy
Requires-Dist: opencv-python
Requires-Dist: pandas
Requires-Dist: pytesseract
Requires-Dist: robotframework
Requires-Dist: scikit-image
Requires-Dist: scikit-learn
Project-URL: Documentation, https://tesena-smart-testing.github.io/WatchUI/
Project-URL: Repository, https://github.com/Tesena-smart-testing/WatchUI
